{"lastUsed":1668409412249,"path":"C:\/Users\/ajsty\/Documents\/Learn\/Selenium\/Java Sel","projectCount":3,"recentFiles":[{"path":"\/demo1\/src\/ajay","parentWorkspace":"C:\/Users\/ajsty\/Documents\/Learn\/Selenium\/Java Sel","name":"Testing_Tooltip_Message.java","lastModified":1668404329290,"locationURI":"file:\/C:\/Users\/ajsty\/Documents\/Learn\/Selenium\/Java%20Sel\/demo1\/src\/ajay\/Testing_Tooltip_Message.java"},{"path":"\/demo1\/src\/ajay","parentWorkspace":"C:\/Users\/ajsty\/Documents\/Learn\/Selenium\/Java Sel","name":"Window_Auth.java","lastModified":1668400595643,"locationURI":"file:\/C:\/Users\/ajsty\/Documents\/Learn\/Selenium\/Java%20Sel\/demo1\/src\/ajay\/Window_Auth.java"},{"path":"\/demo1\/src\/ajay","parentWorkspace":"C:\/Users\/ajsty\/Documents\/Learn\/Selenium\/Java Sel","name":"Integrate_TestNg.java","lastModified":1668404329290,"locationURI":"file:\/C:\/Users\/ajsty\/Documents\/Learn\/Selenium\/Java%20Sel\/demo1\/src\/ajay\/Integrate_TestNg.java"},{"path":"\/demo1\/src","parentWorkspace":"C:\/Users\/ajsty\/Documents\/Learn\/Selenium\/Java Sel","name":"module-info.java","lastModified":1668400297542,"locationURI":"file:\/C:\/Users\/ajsty\/Documents\/Learn\/Selenium\/Java%20Sel\/demo1\/src\/module-info.java"},{"path":"\/demo1\/src\/ajay","parentWorkspace":"C:\/Users\/ajsty\/Documents\/Learn\/Selenium\/Java Sel","name":"Sel1.java","lastModified":1668404329290,"locationURI":"file:\/C:\/Users\/ajsty\/Documents\/Learn\/Selenium\/Java%20Sel\/demo1\/src\/ajay\/Sel1.java"}]}